tkscrollframe/__init__.py
tkscrollframe/scrollFrame.py
tkscrollframe-0.1.1.dist-info/LICENSE
tkscrollframe-0.1.1.dist-info/METADATA
tkscrollframe-0.1.1.dist-info/WHEEL
tkscrollframe-0.1.1.dist-info/top_level.txt
tkscrollframe-0.1.1.dist-info/RECORD
