Metadata-Version: 2.1
Name: tkscrollframe
Version: 0.1.1
Summary: tkinter frame width auto vertical scrollbar
Home-page: https://github.com/youssefhoummad/tkscrollframe
Author: youssef Hoummad
Author-email: youssefhoummad@outlook.com
Project-URL: Bug Tracker, https://github.com/youssefhoummad/tkscrollframe/issues
Classifier: Programming Language :: Python :: 3
Classifier: License :: OSI Approved :: MIT License
Classifier: Operating System :: OS Independent
Requires-Python: >=3.6
License-File: LICENSE
